gcp_commons_utils/__init__.py
gcp_commons_utils/decode.py
gcp_commons_utils/gcp_cache/__init__.py
gcp_commons_utils/gcp_cache/cache_def.py
gcp_commons_utils/gcp_cache/cacher/__init__.py
gcp_commons_utils/gcp_cache/cacher/cache_interface.py
gcp_commons_utils/gcp_cache/cacher/filesystem_cache.py
gcp_commons_utils/gcp_cache/cacher/redis_cache.py
tests/__init__.py
tests/component/__init__.py
tests/component/test_cache.py
tests/integration/__init__.py
tests/unit/__init__.py
gcp_commons_utils-0.1.0.dist-info/LICENSE
gcp_commons_utils-0.1.0.dist-info/METADATA
gcp_commons_utils-0.1.0.dist-info/WHEEL
gcp_commons_utils-0.1.0.dist-info/top_level.txt
gcp_commons_utils-0.1.0.dist-info/RECORD
